paleddon/__init__.py
paleddon/f_installrdf.py
paleddon/f_manifest.py
paleddon/f_overlay_css.py
paleddon/f_overlay_xul.py
paleddon/main.py
Paleddon-1.0.0.dist-info/LICENSE
Paleddon-1.0.0.dist-info/METADATA
Paleddon-1.0.0.dist-info/WHEEL
Paleddon-1.0.0.dist-info/entry_points.txt
Paleddon-1.0.0.dist-info/top_level.txt
Paleddon-1.0.0.dist-info/RECORD
