Metadata-Version: 2.1
Name: Paleddon
Version: 1.0.0
Summary: Tool to create basic addons for Pale Moon with which to have a starting point.
Home-page: https://github.com/Jalkhov/paleddon
Author: Pedro Torcatt
Author-email: ing.torcattsoto.2020@gmail.com
License: UNKNOWN
Project-URL: Bug Reports, https://github.com/Jalkhov/paleddon/issues
Project-URL: Source, https://github.com/Jalkhov/paleddon/
Keywords: xpi pale-moon addon uxp
Platform: UNKNOWN
Classifier: Development Status :: 4 - Beta
Classifier: Programming Language :: Python :: 3
Classifier: Environment :: Console
Classifier: License :: OSI Approved :: MIT License
Requires-Python: >=3.0
License-File: LICENSE
Requires-Dist: click8 (==8.0.1)
Requires-Dist: rstr (==3.0.0)
